j5gnpfweguiwerbngpiutbgn0iutb0pfwef/__init__.py
j5gnpfweguiwerbngpiutbgn0iutb0pfwef-0.0.1.dist-info/METADATA
j5gnpfweguiwerbngpiutbgn0iutb0pfwef-0.0.1.dist-info/WHEEL
j5gnpfweguiwerbngpiutbgn0iutb0pfwef-0.0.1.dist-info/top_level.txt
j5gnpfweguiwerbngpiutbgn0iutb0pfwef-0.0.1.dist-info/RECORD
